{
  "_class": "symbolMaster",
  "allowsOverrides": true,
  "backgroundColor": {
    "_class": "color",
    "alpha": 1,
    "blue": 1,
    "green": 1,
    "red": 1
  },
  "booleanOperation": -1,
  "changeIdentifier": 836,
  "clippingMaskMode": 0,
  "do_objectID": "031DF09E-2A2B-4F00-B06B-EA4030D7277E",
  "exportOptions": {
    "_class": "exportOptions",
    "exportFormats": [
    ],
    "includedLayerIds": [
    ],
    "layerOptions": 0,
    "shouldTrim": false
  },
  "frame": {
    "_class": "rect",
    "constrainProportions": false,
    "height": 48,
    "width": 208,
    "x": -101,
    "y": 2016
  },
  "groupLayout": {
    "_class": "MSImmutableFreeformGroupLayout"
  },
  "hasBackgroundColor": false,
  "hasClickThrough": true,
  "hasClippingMask": false,
  "horizontalRulerData": {
    "_class": "rulerData",
    "base": 0,
    "guides": [
    ]
  },
  "includeBackgroundColorInExport": true,
  "includeBackgroundColorInInstance": false,
  "includeInCloudUpload": true,
  "isFixedToViewport": false,
  "isFlippedHorizontal": false,
  "isFlippedVertical": false,
  "isFlowHome": false,
  "isLocked": false,
  "isVisible": true,
  "layerListExpandedType": 2,
  "layers": [
    {
      "class": "rectangle",
      "id": "C9DEB9EC-03D2-48B7-962B-39D116B3050B"
    },
    {
      "class": "rectangle",
      "id": "19E259A9-DD07-4103-ADDB-96FAC4122FC6"
    },
    {
      "class": "text",
      "id": "E2FBAD9F-C885-4F99-98C1-D16ABDF3D857"
    }
  ],
  "layout": {
    "_class": "layoutGrid",
    "columnWidth": 12.75,
    "drawHorizontal": false,
    "drawHorizontalLines": false,
    "drawVertical": true,
    "gutterHeight": 12,
    "gutterWidth": 5,
    "guttersOutside": false,
    "horizontalOffset": 220,
    "isEnabled": false,
    "numberOfColumns": 12,
    "rowHeightMultiplication": 5,
    "totalWidth": 208
  },
  "name": "button/buttonPrimary/Primary/Hover",
  "nameIsFixed": true,
  "overrideProperties": [
    {
      "_class": "MSImmutableOverrideProperty",
      "canOverride": true,
      "overrideName": "19E259A9-DD07-4103-ADDB-96FAC4122FC6_layerStyle"
    },
    {
      "_class": "MSImmutableOverrideProperty",
      "canOverride": true,
      "overrideName": "E2FBAD9F-C885-4F99-98C1-D16ABDF3D857_textStyle"
    },
    {
      "_class": "MSImmutableOverrideProperty",
      "canOverride": true,
      "overrideName": "C9DEB9EC-03D2-48B7-962B-39D116B3050B_layerStyle"
    },
    {
      "_class": "MSImmutableOverrideProperty",
      "canOverride": true,
      "overrideName": "E2FBAD9F-C885-4F99-98C1-D16ABDF3D857_stringValue"
    }
  ],
  "presetDictionary": {
  },
  "resizesContent": true,
  "resizingConstraint": 63,
  "resizingType": 0,
  "rotation": 0,
  "shouldBreakMaskChain": true,
  "style": {
    "_class": "style",
    "blur": {
      "_class": "blur",
      "center": "{0.5, 0.5}",
      "isEnabled": false,
      "motionAngle": 0,
      "radius": 10,
      "saturation": 1,
      "type": 0
    },
    "borderOptions": {
      "_class": "borderOptions",
      "dashPattern": [
      ],
      "isEnabled": true,
      "lineCapStyle": 0,
      "lineJoinStyle": 0
    },
    "borders": [
    ],
    "colorControls": {
      "_class": "colorControls",
      "brightness": 0,
      "contrast": 1,
      "hue": 0,
      "isEnabled": false,
      "saturation": 1
    },
    "contextSettings": {
      "_class": "graphicsContextSettings",
      "blendMode": 0,
      "opacity": 1
    },
    "do_objectID": "C6208E87-C621-40A6-97C7-9CA8C3D91F0F",
    "endMarkerType": 0,
    "fills": [
    ],
    "innerShadows": [
    ],
    "miterLimit": 10,
    "shadows": [
    ],
    "startMarkerType": 0,
    "windingRule": 1
  },
  "symbolID": "2E5BDC9B-A7BB-492D-B259-93324ACA11AB",
  "verticalRulerData": {
    "_class": "rulerData",
    "base": 0,
    "guides": [
    ]
  }
}